multiparser/__init__.py
multiparser/exceptions.py
multiparser/monitor.py
multiparser/thread.py
multiparser/typing.py
multiparser/parsing/__init__.py
multiparser/parsing/file.py
multiparser/parsing/tail.py
ukaea_multiparser-1.0.5.dist-info/METADATA
ukaea_multiparser-1.0.5.dist-info/WHEEL
ukaea_multiparser-1.0.5.dist-info/licenses/LICENSE
ukaea_multiparser-1.0.5.dist-info/RECORD
