Metadata-Version: 2.4
Name: ukaea-multiparser
Version: 1.0.5
Summary: Multiple File Parser for monitoring and processing updates to a given set of output files.
Author-email: Kristian Zarębski <kristian.zarebski@ukaea.uk>
License: MIT
License-File: LICENSE
Keywords: logging,monitoring,parsing
Classifier: Development Status :: 5 - Production/Stable
Classifier: Intended Audience :: Developers
Classifier: License :: OSI Approved :: MIT License
Classifier: Natural Language :: English
Classifier: Operating System :: Unix
Classifier: Programming Language :: Python :: 3
Classifier: Programming Language :: Python :: 3.10
Classifier: Programming Language :: Python :: 3.11
Classifier: Programming Language :: Python :: 3.12
Classifier: Programming Language :: Python :: 3.13
Classifier: Topic :: System :: Monitoring
Classifier: Typing :: Typed
Requires-Python: <4.0,>=3.10
Requires-Dist: flatdict>=4.0.1
Requires-Dist: loguru>=0.7.3
Requires-Dist: pyyaml>=6.0.2
Requires-Dist: toml>=0.10.2
Provides-Extra: arrow
Requires-Dist: pandas>=2.2.3; extra == 'arrow'
Requires-Dist: pyarrow>=20.0.0; extra == 'arrow'
Requires-Dist: tables>=3.10.1; extra == 'arrow'
Provides-Extra: fortran
Requires-Dist: f90nml>=1.4.5; extra == 'fortran'
